{"__type__":"cc.SpriteAtlas","_name":"voice.plist","_spriteFrames":{"adj":{"__uuid__":"66zziMWSNA5YzZF9AWMjTi"},"cancel":{"__uuid__":"36M02Dd2hKpoEuV9Uvn3On"},"dialog_loading_bg.9":{"__uuid__":"ccp+0mw1pHB6hWiYzVXSIu"},"recorder":{"__uuid__":"b2b8n2a5FOB5Ne/IL0kuot"},"v1":{"__uuid__":"db0kel+DBFbbsf47A7fAB4"},"v2":{"__uuid__":"23lEZBic5NRoUR8k23afg6"},"v3":{"__uuid__":"71MQKJ0jFANbab3CCT1FsZ"},"v4":{"__uuid__":"56WxAepjtDwYh2+ss2akgL"},"v5":{"__uuid__":"22ODnmabdJyoP1zmegV2y1"},"v6":{"__uuid__":"5byD4OP+RCn6OP2ejFStsW"},"v7":{"__uuid__":"cdwEyNx0BDpZHcGJ22V6Y2"},"v_anim1":{"__uuid__":"467DJszBhKg5unSkeHa+ju"},"v_anim2":{"__uuid__":"97WE7+TghMp4QKvMKBTR14"},"v_anim3":{"__uuid__":"f36Z8GL59IHoiO6w1CcDL2"},"voice_to_short":{"__uuid__":"348QhgQ5lBxbFE/W/rDNLS"},"yuyin_bg":{"__uuid__":"c25oiYulhB2p6cRx86Ljwt"},"yyDialog":{"__uuid__":"c4SU50ZxpEBrMCKyvJmx8j"}}}